EOSpython/EOS.py
EOSpython/ID_create.py
EOSpython/LPP_data_setup.py
EOSpython/__init__.py
EOSpython/construct_performance_df.py
EOSpython/distance_matrix.py
EOSpython/easy_funcs.py
EOSpython/electre.py
EOSpython/electre_parallel.py
EOSpython/plot_requests.py
EOSpython/schedule_rel_criteria.py
EOSpython/scipy_sparce_to_spmatrix.py
EOSpython/test.py
EOSpython/worldloc.xlsx
EOSpython-0.0.11.dist-info/LICENSE
EOSpython-0.0.11.dist-info/METADATA
EOSpython-0.0.11.dist-info/WHEEL
EOSpython-0.0.11.dist-info/top_level.txt
EOSpython-0.0.11.dist-info/RECORD
