Metadata-Version: 2.1
Name: EOSpython
Version: 0.0.11
Summary: A set of functions encompassing a centralized Earth Observation Satellite scheduling system
Home-page: https://github.com/AlexVasegaard/EOS
Author: Alex Vasegaard
Author-email: aev@mp.aau.dk
License: MIT
Keywords: satellite,earth observation,operations research,optimization,simulator,scenario generator
Classifier: Programming Language :: Python :: 3
Classifier: License :: OSI Approved :: MIT License
Classifier: Operating System :: OS Independent
Requires-Python: >=3.11, <4
License-File: LICENSE
Requires-Dist: pandas >=2.2.2
Requires-Dist: numpy >=2.0.0
Requires-Dist: ephem >=4.1.5
Requires-Dist: datetime >=5.5
Requires-Dist: requests >=2.32.3
Requires-Dist: folium >=0.17.0
Requires-Dist: scipy >=1.14
Requires-Dist: openpyxl >=3.1.5
Requires-Dist: geopy >=2.4.1
Requires-Dist: cvxopt >=1.3.2
Requires-Dist: gurobipy >=11.0.2
Requires-Dist: pulp >=2.8.0
Provides-Extra: dev
Requires-Dist: twine >=5.1.1 ; extra == 'dev'
